raito/__init__.py
raito/rt.py
raito/core/__init__.py
raito/core/raito.py
raito/core/routers/__init__.py
raito/core/routers/base_router.py
raito/core/routers/loader.py
raito/core/routers/manager.py
raito/core/routers/parser.py
raito/handlers/help.py
raito/handlers/management/list.py
raito/handlers/management/load.py
raito/handlers/management/reload.py
raito/handlers/management/unload.py
raito/handlers/roles/assign.py
raito/handlers/roles/revoke.py
raito/handlers/roles/staff.py
raito/handlers/system/bash.py
raito/handlers/system/eval.py
raito/handlers/system/stats.py
raito/plugins/album/__init__.py
raito/plugins/album/middleware.py
raito/plugins/commands/__init__.py
raito/plugins/commands/flags.py
raito/plugins/commands/middleware.py
raito/plugins/commands/registration.py
raito/plugins/conversations/__init__.py
raito/plugins/conversations/middleware.py
raito/plugins/conversations/registry.py
raito/plugins/conversations/waiter.py
raito/plugins/keyboards/__init__.py
raito/plugins/keyboards/dynamic.py
raito/plugins/keyboards/static.py
raito/plugins/lifespan/decorator.py
raito/plugins/pagination/__init__.py
raito/plugins/pagination/data.py
raito/plugins/pagination/decorator.py
raito/plugins/pagination/enums.py
raito/plugins/pagination/middleware.py
raito/plugins/pagination/util.py
raito/plugins/pagination/paginators/__init__.py
raito/plugins/pagination/paginators/base.py
raito/plugins/pagination/paginators/inline.py
raito/plugins/pagination/paginators/list.py
raito/plugins/pagination/paginators/photo.py
raito/plugins/pagination/paginators/protocol.py
raito/plugins/pagination/paginators/text.py
raito/plugins/roles/__init__.py
raito/plugins/roles/constraint.py
raito/plugins/roles/data.py
raito/plugins/roles/filter.py
raito/plugins/roles/manager.py
raito/plugins/roles/roles.py
raito/plugins/roles/providers/__init__.py
raito/plugins/roles/providers/base.py
raito/plugins/roles/providers/json.py
raito/plugins/roles/providers/memory.py
raito/plugins/roles/providers/protocol.py
raito-1.3.6.dist-info/METADATA
raito-1.3.6.dist-info/WHEEL
raito-1.3.6.dist-info/licenses/LICENSE
raito-1.3.6.dist-info/RECORD
